LICENSE
README.md
gigaleaf/__init__.py
gigaleaf/askpass.py
gigaleaf/gigaleaf.py
gigaleaf/gigantum.py
gigaleaf/linkedfiles/__init__.py
gigaleaf/linkedfiles/csv.py
gigaleaf/linkedfiles/dataframe.py
gigaleaf/linkedfiles/image.py
gigaleaf/linkedfiles/linkedfile.py
gigaleaf/linkedfiles/metadata.py
gigaleaf/overleaf.py
gigaleaf/resources/creds_message.txt
gigaleaf/resources/gigantum_readme.txt
gigaleaf/resources/intro_message.txt
gigaleaf/utils.py
gigaleaf-0.1.6.dist-info/entry_points.txt
gigaleaf-0.1.6.dist-info/LICENSE
gigaleaf-0.1.6.dist-info/WHEEL
gigaleaf-0.1.6.dist-info/METADATA
gigaleaf-0.1.6.dist-info/RECORD
