Metadata-Version: 2.1
Name: gigaleaf
Version: 0.1.6
Summary: An opinionated package for integrating Gigantum and Overleaf Projects
Home-page: https://github.com/gigantum/gigaleaf
License: MIT
Keywords: data-science,latex,gigantum,overleaf
Author: Dean Kleissas
Author-email: dean@gigantum.com
Requires-Python: >=3.7,<4.0
Classifier: License :: OSI Approved :: MIT License
Classifier: Programming Language :: Python :: 3
Classifier: Programming Language :: Python :: 3.7
Classifier: Programming Language :: Python :: 3.8
Provides-Extra: pandas
Requires-Dist: pandas (>=1.0,<2.0); extra == "pandas"
Requires-Dist: requests (>=2.23.0,<3.0.0)
Project-URL: Repository, https://github.com/gigantum/gigaleaf
